[{"Stato":"China","CasiAttivi":1423,"CasiGiornalieri":0,"Popolazione":1439323776,"PercentualeContagi":0.0000988658718578688996797300},{"Stato":"USA","CasiAttivi":27649488,"CasiGiornalieri":0,"Popolazione":334167690,"PercentualeContagi":8.274135659255387616917721760},{"Stato":"India","CasiAttivi":253707,"CasiGiornalieri":0,"Popolazione":1402124607,"PercentualeContagi":0.0180944688320415447926020200},{"Stato":"Brazil","CasiAttivi":2594656,"CasiGiornalieri":0,"Popolazione":215023133,"PercentualeContagi":1.2066869102869968879115904200},{"Stato":"France","CasiAttivi":3342259,"CasiGiornalieri":0,"Popolazione":65509055,"PercentualeContagi":5.1019801766335966836951013900},{"Stato":"UK","CasiAttivi":1865714,"CasiGiornalieri":0,"Popolazione":68467516,"PercentualeContagi":2.7249623018308419426228344500},{"Stato":"Russia","CasiAttivi":2649772,"CasiGiornalieri":0,"Popolazione":146036513,"PercentualeContagi":1.814458552567603418468366200},{"Stato":"Germany","CasiAttivi":3754485,"CasiGiornalieri":0,"Popolazione":84220825,"PercentualeContagi":4.4579057495577845503175728800},{"Stato":"Turkey","CasiAttivi":788296,"CasiGiornalieri":0,"Popolazione":85818603,"PercentualeContagi":0.9185607460890501794814814200},{"Stato":"Italy","CasiAttivi":1404263,"CasiGiornalieri":0,"Popolazione":60316831,"PercentualeContagi":2.3281445273542305297836353500},{"Stato":"Spain","CasiAttivi":2384431,"CasiGiornalieri":0,"Popolazione":46784312,"PercentualeContagi":5.0966464997924945438975355700},{"Stato":"Argentina","CasiAttivi":146408,"CasiGiornalieri":0,"Popolazione":45871952,"PercentualeContagi":0.3191667099756295524550601200},{"Stato":"Iran","CasiAttivi":351432,"CasiGiornalieri":0,"Popolazione":85745427,"PercentualeContagi":0.4098550934967062441708990500},{"Stato":"Colombia","CasiAttivi":44254,"CasiGiornalieri":0,"Popolazione":51767070,"PercentualeContagi":0.0854867775981912826049455800},{"Stato":"Netherlands","CasiAttivi":2313419,"CasiGiornalieri":0,"Popolazione":17196701,"PercentualeContagi":13.452690722482178413173549970},{"Stato":"Poland","CasiAttivi":622913,"CasiGiornalieri":0,"Popolazione":37779009,"PercentualeContagi":1.6488336155138426209115225900},{"Stato":"Mexico","CasiAttivi":439529,"CasiGiornalieri":0,"Popolazione":131141206,"PercentualeContagi":0.3351570520100295554701548200},{"Stato":"Indonesia","CasiAttivi":496383,"CasiGiornalieri":0,"Popolazione":278239007,"PercentualeContagi":0.1784016573923439857589773500},{"Stato":"Ukraine","CasiAttivi":672083,"CasiGiornalieri":0,"Popolazione":43305251,"PercentualeContagi":1.5519665271077634442068006900},{"Stato":"Japan","CasiAttivi":869123,"CasiGiornalieri":0,"Popolazione":125845010,"PercentualeContagi":0.6906296880583505059119944400},{"Stato":"South Africa","CasiAttivi":38210,"CasiGiornalieri":0,"Popolazione":60527644,"PercentualeContagi":0.0631281799106537171676465700},{"Stato":"Philippines","CasiAttivi":65966,"CasiGiornalieri":0,"Popolazione":111958512,"PercentualeContagi":0.0589200399519421980170654600},{"Stato":"Israel","CasiAttivi":152411,"CasiGiornalieri":0,"Popolazione":9326000,"PercentualeContagi":1.6342590606905425691614840200},{"Stato":"Belgium","CasiAttivi":1000437,"CasiGiornalieri":0,"Popolazione":11671874,"PercentualeContagi":8.571348525523836189458522260},{"Stato":"Czechia","CasiAttivi":189130,"CasiGiornalieri":0,"Popolazione":10741381,"PercentualeContagi":1.7607605576973761567530283100},{"Stato":"Canada","CasiAttivi":126165,"CasiGiornalieri":0,"Popolazione":38281696,"PercentualeContagi":0.3295700378583017847485127100},{"Stato":"Malaysia","CasiAttivi":233065,"CasiGiornalieri":0,"Popolazione":33041980,"PercentualeContagi":0.7053602719933853842899245100},{"Stato":"Portugal","CasiAttivi":516890,"CasiGiornalieri":0,"Popolazione":10148221,"PercentualeContagi":5.0934050411397229130110587900},{"Stato":"Australia","CasiAttivi":213221,"CasiGiornalieri":0,"Popolazione":25982211,"PercentualeContagi":0.8206422463430845050099854900},{"Stato":"Chile","CasiAttivi":880670,"CasiGiornalieri":0,"Popolazione":19383746,"PercentualeContagi":4.5433426542011023049930596500},{"Stato":"Vietnam","CasiAttivi":384925,"CasiGiornalieri":0,"Popolazione":98766530,"PercentualeContagi":0.3897322301390967162661278100},{"Stato":"Thailand","CasiAttivi":149586,"CasiGiornalieri":0,"Popolazione":70085604,"PercentualeContagi":0.2134332751131031131585881700},{"Stato":"Switzerland","CasiAttivi":832768,"CasiGiornalieri":0,"Popolazione":8757822,"PercentualeContagi":9.508848204496506094780186220},{"Stato":"Romania","CasiAttivi":332173,"CasiGiornalieri":0,"Popolazione":19028392,"PercentualeContagi":1.745670364579413751829371600},{"Stato":"Austria","CasiAttivi":302866,"CasiGiornalieri":0,"Popolazione":9090194,"PercentualeContagi":3.3317880784502508967355372200},{"Stato":"Sweden","CasiAttivi":680981,"CasiGiornalieri":0,"Popolazione":10201950,"PercentualeContagi":6.6750082092149049936531741500},{"Stato":"Denmark","CasiAttivi":558989,"CasiGiornalieri":0,"Popolazione":5825465,"PercentualeContagi":9.595611680784280739820769670},{"Stato":"Iraq","CasiAttivi":50840,"CasiGiornalieri":0,"Popolazione":41692854,"PercentualeContagi":0.1219393615989924796225271600},{"Stato":"Greece","CasiAttivi":226088,"CasiGiornalieri":0,"Popolazione":10340021,"PercentualeContagi":2.1865332768666523984815891600},{"Stato":"Bangladesh","CasiAttivi":162369,"CasiGiornalieri":0,"Popolazione":167364404,"PercentualeContagi":0.0970152530164060453380516900},{"Stato":"Serbia","CasiAttivi":211571,"CasiGiornalieri":0,"Popolazione":8679973,"PercentualeContagi":2.4374614990161835756862377300},{"Stato":"S. Korea","CasiAttivi":896155,"CasiGiornalieri":0,"Popolazione":51341142,"PercentualeContagi":1.7454909748598891703655520600},{"Stato":"Hungary","CasiAttivi":199303,"CasiGiornalieri":0,"Popolazione":9620346,"PercentualeContagi":2.0716822451084399667122159600},{"Stato":"Jordan","CasiAttivi":189646,"CasiGiornalieri":0,"Popolazione":10368274,"PercentualeContagi":1.8290990380848345635927445600},{"Stato":"Georgia","CasiAttivi":161853,"CasiGiornalieri":0,"Popolazione":3976679,"PercentualeContagi":4.0700544348688943714089067800},{"Stato":"Pakistan","CasiAttivi":70525,"CasiGiornalieri":0,"Popolazione":227881035,"PercentualeContagi":0.0309481655636679024211031900},{"Stato":"Slovakia","CasiAttivi":242552,"CasiGiornalieri":0,"Popolazione":5463955,"PercentualeContagi":4.4391287995600256590693005300},{"Stato":"Kazakhstan","CasiAttivi":38406,"CasiGiornalieri":0,"Popolazione":19142839,"PercentualeContagi":0.2006285483569077710991561900},{"Stato":"Ireland","CasiAttivi":142681,"CasiGiornalieri":0,"Popolazione":5027705,"PercentualeContagi":2.8378952225717300438271537400},{"Stato":"Morocco","CasiAttivi":9355,"CasiGiornalieri":0,"Popolazione":37623761,"PercentualeContagi":0.0248646061726790152637850300},{"Stato":"Norway","CasiAttivi":1028704,"CasiGiornalieri":0,"Popolazione":5490360,"PercentualeContagi":18.736549151603902112065511190},{"Stato":"Cuba","CasiAttivi":3368,"CasiGiornalieri":0,"Popolazione":11315341,"PercentualeContagi":0.0297649005893856844438006800},{"Stato":"Bulgaria","CasiAttivi":247517,"CasiGiornalieri":0,"Popolazione":6863138,"PercentualeContagi":3.6064698101655540075108499900},{"Stato":"Lebanon","CasiAttivi":346393,"CasiGiornalieri":0,"Popolazione":6775596,"PercentualeContagi":5.1123620711742553717783645900},{"Stato":"Croatia","CasiAttivi":28982,"CasiGiornalieri":0,"Popolazione":4063978,"PercentualeContagi":0.7131436243011158032843681700},{"Stato":"Tunisia","CasiAttivi":37703,"CasiGiornalieri":0,"Popolazione":12020234,"PercentualeContagi":0.3136627789442368592824399300},{"Stato":"Nepal","CasiAttivi":14435,"CasiGiornalieri":0,"Popolazione":29990785,"PercentualeContagi":0.0481314510440456960362991500},{"Stato":"Bolivia","CasiAttivi":103616,"CasiGiornalieri":0,"Popolazione":11932568,"PercentualeContagi":0.8683461933759774090539437900},{"Stato":"UAE","CasiAttivi":56874,"CasiGiornalieri":0,"Popolazione":10085204,"PercentualeContagi":0.5639350478185666844220503600},{"Stato":"Slovenia","CasiAttivi":96476,"CasiGiornalieri":0,"Popolazione":2079404,"PercentualeContagi":4.639598654229769684005609300},{"Stato":"Belarus","CasiAttivi":8214,"CasiGiornalieri":0,"Popolazione":9444254,"PercentualeContagi":0.0869735185013024850877581200},{"Stato":"Lithuania","CasiAttivi":95162,"CasiGiornalieri":0,"Popolazione":2660342,"PercentualeContagi":3.5770588894209842193221773700},{"Stato":"Uruguay","CasiAttivi":42678,"CasiGiornalieri":0,"Popolazione":3493362,"PercentualeContagi":1.2216884479764765289139802900},{"Stato":"Costa Rica","CasiAttivi":140531,"CasiGiornalieri":0,"Popolazione":5169960,"PercentualeContagi":2.7182221912742071505388823100},{"Stato":"Azerbaijan","CasiAttivi":37972,"CasiGiornalieri":0,"Popolazione":10288180,"PercentualeContagi":0.3690837446467693994467437400},{"Stato":"Guatemala","CasiAttivi":50313,"CasiGiornalieri":0,"Popolazione":18455595,"PercentualeContagi":0.2726165154794521661317340400},{"Stato":"Panama","CasiAttivi":12190,"CasiGiornalieri":0,"Popolazione":4425467,"PercentualeContagi":0.2754511557763282383531500700},{"Stato":"Saudi Arabia","CasiAttivi":20861,"CasiGiornalieri":0,"Popolazione":35697522,"PercentualeContagi":0.0584382299701363024581930400},{"Stato":"Sri Lanka","CasiAttivi":21745,"CasiGiornalieri":0,"Popolazione":21559660,"PercentualeContagi":0.1008596610521687262229552800},{"Stato":"Paraguay","CasiAttivi":25713,"CasiGiornalieri":0,"Popolazione":7275361,"PercentualeContagi":0.3534257612783750524544417800},{"Stato":"Kuwait","CasiAttivi":23696,"CasiGiornalieri":0,"Popolazione":4373512,"PercentualeContagi":0.5418071334890586787003213900},{"Stato":"Finland","CasiAttivi":556769,"CasiGiornalieri":0,"Popolazione":5554757,"PercentualeContagi":10.023282746662005196626963160},{"Stato":"Dominican Republic","CasiAttivi":2290,"CasiGiornalieri":0,"Popolazione":11025265,"PercentualeContagi":0.0207704758116925080712345700},{"Stato":"Palestine","CasiAttivi":38760,"CasiGiornalieri":0,"Popolazione":5294589,"PercentualeContagi":0.7320681548652784947046881300},{"Stato":"Latvia","CasiAttivi":144773,"CasiGiornalieri":0,"Popolazione":1852188,"PercentualeContagi":7.8163231810161819426537694900},{"Stato":"Myanmar","CasiAttivi":18383,"CasiGiornalieri":0,"Popolazione":55004562,"PercentualeContagi":0.0334208642548594423858879200},{"Stato":"Singapore","CasiAttivi":61283,"CasiGiornalieri":0,"Popolazione":5925363,"PercentualeContagi":1.034248872178801535028318100},{"Stato":"Venezuela","CasiAttivi":11454,"CasiGiornalieri":0,"Popolazione":28304539,"PercentualeContagi":0.0404670077827446686201107200},{"Stato":"Moldova","CasiAttivi":23470,"CasiGiornalieri":0,"Popolazione":4018673,"PercentualeContagi":0.584023631681403289095679100},{"Stato":"Bahrain","CasiAttivi":39798,"CasiGiornalieri":0,"Popolazione":1797844,"PercentualeContagi":2.213651462529563187907293400},{"Stato":"Libya","CasiAttivi":38089,"CasiGiornalieri":0,"Popolazione":7023597,"PercentualeContagi":0.5423004765222150416659725800},{"Stato":"Ethiopia","CasiAttivi":51276,"CasiGiornalieri":0,"Popolazione":119601772,"PercentualeContagi":0.0428722745010834789303957800},{"Stato":"Egypt","CasiAttivi":44573,"CasiGiornalieri":0,"Popolazione":105479457,"PercentualeContagi":0.0422575174993553484068466500},{"Stato":"Mongolia","CasiAttivi":144533,"CasiGiornalieri":0,"Popolazione":3364330,"PercentualeContagi":4.2960411136838538431128932100},{"Stato":"Estonia","CasiAttivi":123071,"CasiGiornalieri":0,"Popolazione":1327990,"PercentualeContagi":9.267464363436471660178163990},{"Stato":"Armenia","CasiAttivi":18824,"CasiGiornalieri":0,"Popolazione":2972275,"PercentualeContagi":0.6333195952595234290232229500},{"Stato":"Honduras","CasiAttivi":268975,"CasiGiornalieri":0,"Popolazione":10161346,"PercentualeContagi":2.6470410514512545877288304100},{"Stato":"Oman","CasiAttivi":18169,"CasiGiornalieri":0,"Popolazione":5318152,"PercentualeContagi":0.3416412317662225524956789500},{"Stato":"Bosnia and Herzegovina","CasiAttivi":160160,"CasiGiornalieri":0,"Popolazione":3247537,"PercentualeContagi":4.9317374982948616135859268100},{"Stato":"Qatar","CasiAttivi":6280,"CasiGiornalieri":0,"Popolazione":2807805,"PercentualeContagi":0.2236622557478172451434483500},{"Stato":"Kenya","CasiAttivi":14041,"CasiGiornalieri":0,"Popolazione":55700843,"PercentualeContagi":0.0252078770154340393017032100},{"Stato":"Zambia","CasiAttivi":2622,"CasiGiornalieri":0,"Popolazione":19222348,"PercentualeContagi":0.0136403731739743760751808300},{"Stato":"Cyprus","CasiAttivi":177562,"CasiGiornalieri":0,"Popolazione":1221690,"PercentualeContagi":14.534128952516595863107662340},{"Stato":"North Macedonia","CasiAttivi":8143,"CasiGiornalieri":0,"Popolazione":2083235,"PercentualeContagi":0.3908824496516235566318730200},{"Stato":"R&eacute;union","CasiAttivi":27532,"CasiGiornalieri":0,"Popolazione":905730,"PercentualeContagi":3.0397579852715489163437227400},{"Stato":"Albania","CasiAttivi":6170,"CasiGiornalieri":0,"Popolazione":2872672,"PercentualeContagi":0.2147826135388934065566831200},{"Stato":"Algeria","CasiAttivi":80608,"CasiGiornalieri":0,"Popolazione":45141381,"PercentualeContagi":0.1785678643726030446432287900},{"Stato":"Botswana","CasiAttivi":2867,"CasiGiornalieri":0,"Popolazione":2428989,"PercentualeContagi":0.1180326465043686900187691300},{"Stato":"Nigeria","CasiAttivi":20530,"CasiGiornalieri":0,"Popolazione":214461276,"PercentualeContagi":0.0095728237670282256457338200},{"Stato":"Uzbekistan","CasiAttivi":10182,"CasiGiornalieri":0,"Popolazione":34259819,"PercentualeContagi":0.0297199468566953024474530900},{"Stato":"Zimbabwe","CasiAttivi":2972,"CasiGiornalieri":0,"Popolazione":15215580,"PercentualeContagi":0.01953261065302801470597900},{"Stato":"Montenegro","CasiAttivi":2763,"CasiGiornalieri":0,"Popolazione":628196,"PercentualeContagi":0.4398308808079007188839152100},{"Stato":"Mozambique","CasiAttivi":3752,"CasiGiornalieri":0,"Popolazione":32681373,"PercentualeContagi":0.0114805458142777538752732300},{"Stato":"Kyrgyzstan","CasiAttivi":3524,"CasiGiornalieri":0,"Popolazione":6699617,"PercentualeContagi":0.052600021762438061757858700},{"Stato":"Luxembourg","CasiAttivi":13537,"CasiGiornalieri":0,"Popolazione":642575,"PercentualeContagi":2.1066801540676185659261564800},{"Stato":"Afghanistan","CasiAttivi":13139,"CasiGiornalieri":0,"Popolazione":40356532,"PercentualeContagi":0.0325573069559098883917973900},{"Stato":"Maldives","CasiAttivi":15381,"CasiGiornalieri":0,"Popolazione":556058,"PercentualeContagi":2.7660783587323624513989547900},{"Stato":"Uganda","CasiAttivi":59636,"CasiGiornalieri":0,"Popolazione":48092721,"PercentualeContagi":0.1240021332958058247525649500},{"Stato":"Ghana","CasiAttivi":358,"CasiGiornalieri":0,"Popolazione":32129679,"PercentualeContagi":0.0011142345991069503059772200},{"Stato":"Namibia","CasiAttivi":530,"CasiGiornalieri":0,"Popolazione":2615889,"PercentualeContagi":0.0202607985277662775446511700},{"Stato":"El Salvador","CasiAttivi":19884,"CasiGiornalieri":0,"Popolazione":6539573,"PercentualeContagi":0.3040565492578796811351444500},{"Stato":"Laos","CasiAttivi":132339,"CasiGiornalieri":0,"Popolazione":7447641,"PercentualeContagi":1.7769250692937535522993119600},{"Stato":"Rwanda","CasiAttivi":82383,"CasiGiornalieri":0,"Popolazione":13475165,"PercentualeContagi":0.6113691372239226755293905500},{"Stato":"Jamaica","CasiAttivi":50138,"CasiGiornalieri":0,"Popolazione":2982243,"PercentualeContagi":1.6812177947940526643871743500},{"Stato":"Cambodia","CasiAttivi":2306,"CasiGiornalieri":0,"Popolazione":17096118,"PercentualeContagi":0.0134884422299846082016981900},{"Stato":"Guadeloupe","CasiAttivi":120544,"CasiGiornalieri":0,"Popolazione":400236,"PercentualeContagi":30.118230244155947990685495560},{"Stato":"Trinidad and Tobago","CasiAttivi":20731,"CasiGiornalieri":0,"Popolazione":1406878,"PercentualeContagi":1.4735463913715332814927804700},{"Stato":"Cameroon","CasiAttivi":11137,"CasiGiornalieri":0,"Popolazione":27622124,"PercentualeContagi":0.0403191296947331059696929900},{"Stato":"Martinique","CasiAttivi":107384,"CasiGiornalieri":0,"Popolazione":374790,"PercentualeContagi":28.651778329197684036393713810},{"Stato":"Iceland","CasiAttivi":26343,"CasiGiornalieri":0,"Popolazione":344854,"PercentualeContagi":7.638884861419615257471277700},{"Stato":"Angola","CasiAttivi":197,"CasiGiornalieri":0,"Popolazione":34530727,"PercentualeContagi":0.0005705063782757889806374500},{"Stato":"DRC","CasiAttivi":33588,"CasiGiornalieri":0,"Popolazione":93994533,"PercentualeContagi":0.0357339931674536858436224200},{"Stato":"Senegal","CasiAttivi":141,"CasiGiornalieri":0,"Popolazione":17462523,"PercentualeContagi":0.0008074434604896440222297800},{"Stato":"Malawi","CasiAttivi":8148,"CasiGiornalieri":0,"Popolazione":19935031,"PercentualeContagi":0.0408727731599715094498724400},{"Stato":"Ivory Coast","CasiAttivi":1402,"CasiGiornalieri":0,"Popolazione":27442189,"PercentualeContagi":0.0051089218866614467235102900},{"Stato":"Suriname","CasiAttivi":26896,"CasiGiornalieri":0,"Popolazione":595202,"PercentualeContagi":4.5188020201545021690115288600},{"Stato":"French Guiana","CasiAttivi":65813,"CasiGiornalieri":0,"Popolazione":311290,"PercentualeContagi":21.142021908830993607247261400},{"Stato":"Malta","CasiAttivi":1400,"CasiGiornalieri":0,"Popolazione":443461,"PercentualeContagi":0.3156985619930501216566958500},{"Stato":"Eswatini","CasiAttivi":192,"CasiGiornalieri":0,"Popolazione":1179748,"PercentualeContagi":0.0162746620464709412518605700},{"Stato":"Fiji","CasiAttivi":1012,"CasiGiornalieri":0,"Popolazione":907037,"PercentualeContagi":0.111572074788569815784802600},{"Stato":"Madagascar","CasiAttivi":5009,"CasiGiornalieri":0,"Popolazione":28850425,"PercentualeContagi":0.0173619626054035599128955600},{"Stato":"Guyana","CasiAttivi":952,"CasiGiornalieri":0,"Popolazione":792741,"PercentualeContagi":0.1200896635849539761410094800},{"Stato":"Sudan","CasiAttivi":15779,"CasiGiornalieri":0,"Popolazione":45516978,"PercentualeContagi":0.0346661854396396878544968400},{"Stato":"Mauritania","CasiAttivi":144,"CasiGiornalieri":0,"Popolazione":4848700,"PercentualeContagi":0.0029698682120980881473384600},{"Stato":"Belize","CasiAttivi":2443,"CasiGiornalieri":0,"Popolazione":409391,"PercentualeContagi":0.5967400358092874538033322700},{"Stato":"Cabo Verde","CasiAttivi":74,"CasiGiornalieri":0,"Popolazione":565832,"PercentualeContagi":0.0130780867819423433103818800},{"Stato":"Syria","CasiAttivi":5520,"CasiGiornalieri":0,"Popolazione":18193124,"PercentualeContagi":0.0303411332765060030371914100},{"Stato":"Barbados","CasiAttivi":4460,"CasiGiornalieri":0,"Popolazione":287949,"PercentualeContagi":1.5488853928994370530892623300},{"Stato":"Channel Islands","CasiAttivi":2867,"CasiGiornalieri":0,"Popolazione":176476,"PercentualeContagi":1.6245835127722749835671706100},{"Stato":"Gabon","CasiAttivi":2182,"CasiGiornalieri":0,"Popolazione":2311281,"PercentualeContagi":0.0944065217513577968234931200},{"Stato":"New Caledonia","CasiAttivi":13791,"CasiGiornalieri":0,"Popolazione":289973,"PercentualeContagi":4.7559600376586785666251685500},{"Stato":"Hong Kong","CasiAttivi":27210,"CasiGiornalieri":0,"Popolazione":7596152,"PercentualeContagi":0.3582076819947784088575373400},{"Stato":"Papua New Guinea","CasiAttivi":1448,"CasiGiornalieri":0,"Popolazione":9223184,"PercentualeContagi":0.0156995675246205648721742900},{"Stato":"Seychelles","CasiAttivi":804,"CasiGiornalieri":0,"Popolazione":99340,"PercentualeContagi":0.8093416549224884235957318300},{"Stato":"Cura&ccedil;ao","CasiAttivi":666,"CasiGiornalieri":0,"Popolazione":165187,"PercentualeContagi":0.4031794269524841543220713500},{"Stato":"Burundi","CasiAttivi":37136,"CasiGiornalieri":0,"Popolazione":12467396,"PercentualeContagi":0.2978649270465139633007566300},{"Stato":"Andorra","CasiAttivi":771,"CasiGiornalieri":0,"Popolazione":77467,"PercentualeContagi":0.995262498870486787922599300},{"Stato":"Togo","CasiAttivi":175,"CasiGiornalieri":0,"Popolazione":8594784,"PercentualeContagi":0.0020361186505676000699959400},{"Stato":"Mayotte","CasiAttivi":33480,"CasiGiornalieri":0,"Popolazione":283537,"PercentualeContagi":11.807982732412348300221840540},{"Stato":"Guinea","CasiAttivi":3232,"CasiGiornalieri":0,"Popolazione":13712901,"PercentualeContagi":0.0235690464038207524432649200},{"Stato":"Aruba","CasiAttivi":65,"CasiGiornalieri":0,"Popolazione":107505,"PercentualeContagi":0.0604623040788800520906004400},{"Stato":"Bahamas","CasiAttivi":6513,"CasiGiornalieri":0,"Popolazione":399370,"PercentualeContagi":1.6308185391992388011117510100},{"Stato":"Lesotho","CasiAttivi":8622,"CasiGiornalieri":0,"Popolazione":2169939,"PercentualeContagi":0.3973383583593824526864580100},{"Stato":"Brunei","CasiAttivi":11731,"CasiGiornalieri":0,"Popolazione":444309,"PercentualeContagi":2.6402796252157845103295229200},{"Stato":"Faeroe Islands","CasiAttivi":22854,"CasiGiornalieri":0,"Popolazione":49166,"PercentualeContagi":46.483342147012162876784769960},{"Stato":"Mali","CasiAttivi":1190,"CasiGiornalieri":0,"Popolazione":21200598,"PercentualeContagi":0.0056130492168192614189467700},{"Stato":"Haiti","CasiAttivi":4196,"CasiGiornalieri":0,"Popolazione":11629125,"PercentualeContagi":0.0360818204293100297743811300},{"Stato":"Mauritius","CasiAttivi":2632,"CasiGiornalieri":0,"Popolazione":1275210,"PercentualeContagi":0.206397377686812368158969900},{"Stato":"New Zealand","CasiAttivi":10412,"CasiGiornalieri":0,"Popolazione":5002100,"PercentualeContagi":0.2081525759181143919553787400},{"Stato":"Benin","CasiAttivi":898,"CasiGiornalieri":0,"Popolazione":12640345,"PercentualeContagi":0.0071042364745582497946060800},{"Stato":"Somalia","CasiAttivi":11733,"CasiGiornalieri":0,"Popolazione":16615271,"PercentualeContagi":0.0706157606457336747622112200},{"Stato":"Congo","CasiAttivi":3321,"CasiGiornalieri":0,"Popolazione":5739312,"PercentualeContagi":0.0578640784818807550452040200},{"Stato":"Saint Lucia","CasiAttivi":1068,"CasiGiornalieri":0,"Popolazione":184996,"PercentualeContagi":0.5773097796709118034984540200},{"Stato":"Isle of Man","CasiAttivi":218,"CasiGiornalieri":0,"Popolazione":85767,"PercentualeContagi":0.2541770144694346310352466600},{"Stato":"Timor-Leste","CasiAttivi":1515,"CasiGiornalieri":0,"Popolazione":1359363,"PercentualeContagi":0.1114492596900165739394113300},{"Stato":"Burkina Faso","CasiAttivi":60,"CasiGiornalieri":0,"Popolazione":21836685,"PercentualeContagi":0.0002747669804276610666866300},{"Stato":"Taiwan","CasiAttivi":1183,"CasiGiornalieri":0,"Popolazione":23887075,"PercentualeContagi":0.0049524690653836855286802600},{"Stato":"Cayman Islands","CasiAttivi":10158,"CasiGiornalieri":0,"Popolazione":66980,"PercentualeContagi":15.165721110779337115556882650},{"Stato":"Nicaragua","CasiAttivi":13451,"CasiGiornalieri":0,"Popolazione":6753039,"PercentualeContagi":0.1991843968323002428980493100},{"Stato":"Tajikistan","CasiAttivi":12,"CasiGiornalieri":0,"Popolazione":9886621,"PercentualeContagi":0.0001213761506585515920960300},{"Stato":"South Sudan","CasiAttivi":3689,"CasiGiornalieri":0,"Popolazione":11407667,"PercentualeContagi":0.0323379004664143860440526500},{"Stato":"Equatorial Guinea","CasiAttivi":68,"CasiGiornalieri":0,"Popolazione":1478018,"PercentualeContagi":0.0046007558771273421568614200},{"Stato":"Djibouti","CasiAttivi":8,"CasiGiornalieri":0,"Popolazione":1011418,"PercentualeContagi":0.0007909687191645788388183700},{"Stato":"Gibraltar","CasiAttivi":779,"CasiGiornalieri":0,"Popolazione":33675,"PercentualeContagi":2.3132887899034892353377876800},{"Stato":"CAR","CasiAttivi":7215,"CasiGiornalieri":0,"Popolazione":4966612,"PercentualeContagi":0.1452700553214142759692120100},{"Stato":"San Marino","CasiAttivi":652,"CasiGiornalieri":0,"Popolazione":34047,"PercentualeContagi":1.9149998531441830410902575900},{"Stato":"Grenada","CasiAttivi":307,"CasiGiornalieri":0,"Popolazione":113373,"PercentualeContagi":0.2707875772891252767413758100},{"Stato":"Gambia","CasiAttivi":98,"CasiGiornalieri":0,"Popolazione":2527225,"PercentualeContagi":0.0038777710730148680865376100},{"Stato":"Yemen","CasiAttivi":1061,"CasiGiornalieri":0,"Popolazione":30896104,"PercentualeContagi":0.0034340899422140733342948400},{"Stato":"Greenland","CasiAttivi":8774,"CasiGiornalieri":0,"Popolazione":56931,"PercentualeContagi":15.411638650295972317366636810},{"Stato":"Bermuda","CasiAttivi":211,"CasiGiornalieri":0,"Popolazione":61903,"PercentualeContagi":0.3408558551281844175564996800},{"Stato":"Liechtenstein","CasiAttivi":419,"CasiGiornalieri":0,"Popolazione":38306,"PercentualeContagi":1.0938234219182373518508849800},{"Stato":"Dominica","CasiAttivi":797,"CasiGiornalieri":0,"Popolazione":72278,"PercentualeContagi":1.1026868480035418799634743600},{"Stato":"Saint Martin","CasiAttivi":8365,"CasiGiornalieri":0,"Popolazione":39741,"PercentualeContagi":21.048790921214866259027201130},{"Stato":"Eritrea","CasiAttivi":30,"CasiGiornalieri":0,"Popolazione":3626427,"PercentualeContagi":0.0008272605515015192640028300},{"Stato":"Sint Maarten","CasiAttivi":100,"CasiGiornalieri":0,"Popolazione":43670,"PercentualeContagi":0.2289901534234027936798717700},{"Stato":"Bhutan","CasiAttivi":3117,"CasiGiornalieri":0,"Popolazione":785459,"PercentualeContagi":0.3968380271917439357114757100},{"Stato":"Monaco","CasiAttivi":188,"CasiGiornalieri":0,"Popolazione":39696,"PercentualeContagi":0.4735993550987505038291011700},{"Stato":"Niger","CasiAttivi":26,"CasiGiornalieri":0,"Popolazione":25632730,"PercentualeContagi":0.0001014328165591413790103500},{"Stato":"Comoros","CasiAttivi":77,"CasiGiornalieri":0,"Popolazione":899780,"PercentualeContagi":0.0085576474249260930449665500},{"Stato":"Guinea-Bissau","CasiAttivi":810,"CasiGiornalieri":0,"Popolazione":2043767,"PercentualeContagi":0.0396326978564581970449664800},{"Stato":"Caribbean Netherlands","CasiAttivi":121,"CasiGiornalieri":0,"Popolazione":26620,"PercentualeContagi":0.4545454545454545454545454500},{"Stato":"Antigua and Barbuda","CasiAttivi":76,"CasiGiornalieri":0,"Popolazione":99251,"PercentualeContagi":0.0765735357830147807074991700},{"Stato":"Liberia","CasiAttivi":1323,"CasiGiornalieri":0,"Popolazione":5251317,"PercentualeContagi":0.0251936799854208001535614800},{"Stato":"Chad","CasiAttivi":2150,"CasiGiornalieri":0,"Popolazione":17193353,"PercentualeContagi":0.0125048325361551059877616700},{"Stato":"St. Vincent Grenadines","CasiAttivi":76,"CasiGiornalieri":0,"Popolazione":111515,"PercentualeContagi":0.0681522665112316728691207500},{"Stato":"Sao Tome and Principe","CasiAttivi":10,"CasiGiornalieri":0,"Popolazione":225791,"PercentualeContagi":0.0044288744901258243242644700},{"Stato":"Turks and Caicos","CasiAttivi":45,"CasiGiornalieri":0,"Popolazione":39571,"PercentualeContagi":0.1137196431730307548457203500},{"Stato":"Solomon Islands","CasiAttivi":4275,"CasiGiornalieri":0,"Popolazione":714320,"PercentualeContagi":0.5984712733788778138649344800},{"Stato":"Saint Kitts and Nevis","CasiAttivi":29,"CasiGiornalieri":0,"Popolazione":53813,"PercentualeContagi":0.0538903238994295058814784500},{"Stato":"Palau","CasiAttivi":973,"CasiGiornalieri":0,"Popolazione":18235,"PercentualeContagi":5.3358925143953934740882917500},{"Stato":"Kiribati","CasiAttivi":2086,"CasiGiornalieri":0,"Popolazione":122436,"PercentualeContagi":1.703747263876637590251233300},{"Stato":"Anguilla","CasiAttivi":21,"CasiGiornalieri":0,"Popolazione":15221,"PercentualeContagi":0.1379672820445437224886669700},{"Stato":"Saint Pierre Miquelon","CasiAttivi":33,"CasiGiornalieri":0,"Popolazione":5748,"PercentualeContagi":0.5741127348643006263048016700},{"Stato":"Wallis and Futuna","CasiAttivi":9,"CasiGiornalieri":0,"Popolazione":10918,"PercentualeContagi":0.0824326799780179520058618800},{"Stato":"Tonga","CasiAttivi":201,"CasiGiornalieri":0,"Popolazione":107648,"PercentualeContagi":0.1867196789536266349583828800},{"Stato":"Samoa","CasiAttivi":30,"CasiGiornalieri":0,"Popolazione":200564,"PercentualeContagi":0.0149578189505594224287509200},{"Stato":"Vatican City","CasiAttivi":1,"CasiGiornalieri":0,"Popolazione":804,"PercentualeContagi":0.124378109452736318407960200},{"Stato":"Vanuatu","CasiAttivi":4,"CasiGiornalieri":0,"Popolazione":318836,"PercentualeContagi":0.0012545634746389993601726300},{"Stato":"Western Sahara","CasiAttivi":1,"CasiGiornalieri":0,"Popolazione":621260,"PercentualeContagi":0.0001609632038116086662588900},{"Stato":"Cook Islands","CasiAttivi":4,"CasiGiornalieri":0,"Popolazione":17590,"PercentualeContagi":0.0227401932916429789653212100}]